Workbook

Sheet Section Audit
A1: ID | B1: Site Tab | C1: Page | D1: File | E1: Section | F1: Type | G1: Current Content (from delivered site) | H1: Rewritten copy (short/medium only — long copy in Doc) | I1: Primary keyword | J1: Secondary keywords | K1: Intent | L1: AEO question(s) | M1: Status | N1: Client feedback | O1: Doc link | P1: Notes / Source
A2: GLB-01 | B2: Global (all pages) | C2: Header & Navigation | D2: index.html (all pages) | E2: Top nav (left): Home | Developments (dropdown: Seven X Seven, Emerald Villa, Dubai Hills Mansion) | About. Top nav (right): Legacy | Media (dropdown: News, Investor Guide) | Contact. Button: 'Book online call' (opens Inquiry Form modal). Brand logo links to Home. Mobile menu mirrors the same items. | F2: Nav | G2: Same header markup on every page. | H2: Keep as-is - structural (no copy change recommended). | K2: Navigational | L2: Nav labels stay; add descriptive title attributes on dropdown items in Phase 2. | M2: Drafted | O2: 00-globals.docx
A3: GLB-02 | B3: Global (all pages) | C3: Footer | D3: index.html (all pages) | E3: Development: Seven X Seven Residences, Emerald Villa, Dubai Hills Mansion. Company: About Us, Legacy, Investor Guide. Media: News & Updates, Contact Us. Newsletter: 'Stay in the know' — Email Address input + Submit; consent text: 'By signing up, I agree to receive KPD updates and accept the privacy policy.' Legal: Terms of Use, Privacy, Cookie Policy. Social: Facebook, X, Instagram, YouTube. Copyright: 'Kasumigaseki Properties Development © 2026'. | F3: Footer | G3: Same footer on every page. | H3: Footer copy updated: brand line 'Turning challenge into value.' above newsletter. Consent text: 'By signing up, I agree to receive KPD updates and accept the privacy policy.' Legal/social links unchanged. | I3: Kasumigaseki Properties Development | K3: Navigational | L3: Footer is a crawl anchor; keep exact project names (Seven X Seven Residences, Emerald Villa, Dubai Hills Mansion) as internal links. | M3: Drafted | O3: 00-globals.docx
A4: GLB-03 | B4: Global (all pages) | C4: Inquiry Form modal (Book online call) | D4: index.html (all pages) | E4: Title: 'Inquiry Form'. Intro: 'Share a few contact details and the KPD team will coordinate the right advisory conversation.' Fields: Full name, Email address, Phone number, Interested in (Seven X Seven, Emerald Villa, Dubai Hills Mansion, Online call), Message (short). Submit: 'Submit inquiry'. Note: 'The KPD team will respond with the right advisory route.' | F4: Form | G4: Form posts to mailto:info@kpd.ae | H4: Intro: 'Share a few details and the KPD team will arrange the right advisory conversation - direct, unhurried, and without obligation.' Note: 'A member of the team will respond personally.' Fields unchanged. | K4: Transactional | L4: Modal is a conversion surface, not a ranking surface; keep microcopy reassuring (Anshin). | M4: Drafted | O4: 00-globals.docx
A5: HOM-01 | B5: Home | C5: Home | D5: index.html | E5: Turning Challenge Into Value (id: about) | F5: Body | G5: KPD extends Kasumigaseki Capital's development, investment, and asset-management discipline into Dubai, pairing long-term capital with a carefully curated residential pipeline. Established to extend that legacy into one of the world's most dynamic property markets, KPD brings institutional discipline, long-term capital, and a decades-deep development track record to the UAE - delivering projects built not just for today's market, but for generations ahead. $4.4BGlobal AUM $320MDubai Real Estate $2.27BLogistics $1.64BHotels (As of February, 2026) Stats (as of February, 2026): $4.4B — Global AUM | $320M — Dubai Real Estate | $2.27B — Logistics | $1.64B — Hotels | H5: Long copy - full rewrite in the page Doc (content/google-doc-templates/). | I5: Dubai property developer | J5: Japanese property developer Dubai; Kasumigaseki Properties Development | K5: Commercial | L5: Who is Kasumigaseki Properties Development? Answer in first sentence: Dubai real estate arm of Tokyo-listed Kasumigaseki Capital. | M5: Drafted | O5: 01-home.docx
A6: HOM-02 | B6: Home | C6: Home | D6: index.html | E6: Our Developments (id: developments) | F6: Body | G6: Explore | H6: Section lead: 'Three addresses. One standard. Residences, villas and mansions across Dubai's most considered districts.' Button: Explore. | I6: KPD developments Dubai | K6: Commercial | L6: What is KPD developing in Dubai? Name the three projects plainly. | M6: Drafted | O6: 01-home.docx
A7: HOM-03 | B7: Home | C7: Home | D7: index.html | E7: Seven X Seven (id: development-cards) | F7: Body | G7: A composed Meydan Horizon residence shaped by arrival, light, privacy, and efficient access to Dubai's core districts. Explore | H7: 'Seven X Seven Residences - a composed Meydan Horizon address shaped by arrival, light, privacy and measured access to Dubai's core districts.' Button: Explore. | I7: Seven X Seven Residences | J7: Meydan Horizon residence | K7: Commercial | L7: Alt/aria text: 'Seven X Seven Residences, Meydan Horizon, Dubai - KPD development'. | M7: Drafted | O7: 01-home.docx
A8: HOM-04 | B8: Home | C8: Home | D8: index.html | E8: Emerald Villa (id: development-cards) | F8: Body | G8: A private villa composition shaped around garden arrival, layered privacy, and family-scaled living. Explore | H8: 'Emerald Villa - a garden-led private villa shaped around planted arrival, layered privacy and family-scaled living.' Button: Explore. | I8: Emerald Villa Dubai | J8: private garden villa Dubai | K8: Commercial | L8: Alt/aria text: 'Emerald Villa - private garden villa in Dubai by KPD'. | M8: Drafted | O8: 01-home.docx
A9: HOM-05 | B9: Home | C9: Home | D9: index.html | E9: Dubai Hills Mansion (id: development-cards) | F9: Body | G9: A mansion-scale residence organized around garden arrival, private wellness, and long-horizon family living. Explore | H9: 'Dubai Hills Mansion - a mansion-scale residence organized around garden arrival, private wellness and long-horizon family living.' Button: Explore. | I9: Dubai Hills Mansion | J9: Dubai Hills Estate mansion | K9: Commercial | L9: Alt/aria text: 'Dubai Hills Mansion - mansion residence in Dubai Hills Estate by KPD'. | M9: Drafted | O9: 01-home.docx
A10: HOM-06 | B10: Home | C10: Home | D10: index.html | E10: A first point of contact (id: contact) | F10: Body | G10: The Experience Center is designed for focused project previews, private advisory conversations, model walkthroughs, and material review in one calm appointment-led setting. Plan Visit | H10: 'The KPD Experience Center is designed for focused project previews, private advisory conversations, model walkthroughs and material review - one calm, appointment-led setting.' Button: Plan Visit. | I10: KPD Experience Center | K10: Commercial | L10: Where can I view KPD projects in Dubai? -> The Experience Center (address on Contact page). | M10: Drafted | O10: 01-home.docx
A11: HOM-07 | B11: Home | C11: Home | D11: index.html | E11: Blogs and updates (id: events) | F11: Body | G11: Announcements, market observations, and development commentary are presented as a quiet editorial layer rather than a busy newsroom wall. Explore | H11: 'Announcements, market observations and development commentary - a quiet editorial layer, not a busy newsroom.' Button: Explore. | I11: KPD blog | K11: Informational | L11: Where does KPD publish news and market notes? -> /news | M11: Drafted | O11: 01-home.docx
A12: HOM-08 | B12: Home | C12: Home | D12: index.html | E12: Design, Underwriting & Endurance Forum | F12: Body | G12: A market note on how disciplined feasibility, measured design, and delivery control shape long-horizon residential value. Explore | H12: 'A closed-room forum on how disciplined feasibility, measured design and delivery control shape long-horizon residential value.' Button: Explore. | I12: Dubai real estate forum | K12: Informational | M12: Drafted | O12: 01-home.docx
A13: HOM-09 | B13: Home | C13: Home | D13: index.html | E13: Experience Center Private Preview | F13: Body | G13: A private look at the spaces, materials, and consultation flow inside the KPD Experience Center. Explore | H13: 'A private look at the spaces, materials and consultation flow inside the KPD Experience Center.' Button: Explore. | I13: KPD Experience Center | K13: Informational | M13: Drafted | O13: 01-home.docx
A14: HOM-10 | B14: Home | C14: Home | D14: index.html | E14: Emerald Villa Private Preview | F14: Body | G14: A preview of garden-led villa living, privacy planning, and hospitality cues within the Emerald Villa collection. Explore | H14: 'A preview of garden-led villa living, privacy planning and hospitality cues within the Emerald Villa collection.' Button: Explore. | I14: Emerald Villa preview | K14: Commercial | M14: Drafted | O14: 01-home.docx
A15: HOM-11 | B15: Home | C15: Home | D15: index.html | E15: Turning Challenge Into Value (id: collection) | F15: Body | G15: Discover The Collection Kasumigaseki Properties Development | H15: 'Discover The Collection - Kasumigaseki Properties Development.' Eyebrow: The Collection. | K15: Commercial | M15: Drafted | O15: 01-home.docx
A16: HOM-12 | B16: Home | C16: Home | D16: index.html | E16: A disciplined platform for Dubai's next enduring addresses. | F16: Body | G16: KPD brings Kasumigaseki Capital's development discipline, investment rigor, and asset-management experience into a focused Dubai property platform. KPD extends that institutional legacy into one of the world's most dynamic property markets with residential, hospitality, and mixed-use projects designed for long-term value. USD 5B+Parent platform assets under management TokyoListed institutional development heritage DubaiUAE development market focus 3+Residential and hospitality-led pathways (As of February, 2026) | H16: Long copy - full rewrite in the page Doc (content/google-doc-templates/). | I16: Dubai property platform | J16: residential hospitality mixed-use Dubai | K16: Commercial | L16: What does KPD build? Residential, hospitality and mixed-use - same standard at every price point. | M16: Drafted | O16: 01-home.docx
A17: HOM-13 | B17: Home | C17: Home | D17: index.html | E17: The Collection | F17: Body | G17: View Developments | H17: 'The Collection - three current addresses from the KPD pipeline.' Button: View Developments. | K17: Commercial | M17: Drafted | O17: 01-home.docx
A18: HOM-14 | B18: Home | C18: Home | D18: index.html | E18: Seven X Seven | F18: Body | G18: A residential address shaped around measured city access, privacy, and everyday liveability. Explore | H18: 'A residential address shaped around measured city access, privacy and everyday liveability.' Button: Explore. | I18: Seven X Seven Residences | K18: Commercial | M18: Drafted | O18: 01-home.docx
A19: HOM-15 | B19: Home | C19: Home | D19: index.html | E19: Emerald Villa | F19: Body | G19: A garden-led villa address shaped around privacy, wellness, and family-scaled living. Explore | H19: 'A garden-led villa address shaped around privacy, wellness and family-scaled living.' Button: Explore. | I19: Emerald Villa Dubai | K19: Commercial | M19: Drafted | O19: 01-home.docx
A20: HOM-16 | B20: Home | C20: Home | D20: index.html | E20: Dubai Hills Mansion | F20: Body | G20: A mansion-scale residence shaped around garden arrival, private wellness, and long-horizon family living. Explore Experience Center | H20: 'A mansion-scale residence shaped around garden arrival, private wellness and long-horizon family living.' Button: Explore. | I20: Dubai Hills Mansion | K20: Commercial | M20: Drafted | O20: 01-home.docx
A21: HOM-17 | B21: Home | C21: Home | D21: index.html | E21: A first point of contact for project briefings and private advisory conversations. | F21: Body | G21: KPD's client-facing experience is arranged around clarity: project previews, buyer support, capital dialogue, and channel partner access are routed through a single appointment-led environment. Start An Inquiry KPD Experience Center | H21: 'KPD's client-facing experience is arranged around clarity: project previews, buyer support, capital dialogue and channel-partner access, routed through a single appointment-led environment.' Buttons: Start An Inquiry / KPD Experience Center. | K21: Commercial | M21: Drafted | O21: 01-home.docx
A22: HOM-18 | B22: Home | C22: Home | D22: index.html | E22: Project briefings, advisory meetings, and private previews in one calm setting. | F22: Body | G22: View Gallery Private Consultation Model Walkthrough Delivery Workspace Asset Performance Platform Note | H22: 'Project briefings, advisory meetings and private previews in one calm setting.' Sequence kept: Private Consultation / Model Walkthrough / Delivery Workspace / Asset Performance. Label: Platform Note. | K22: Commercial | M22: Drafted | O22: 01-home.docx
A23: HOM-19 | B23: Home | C23: Home | D23: index.html | E23: Developing land logic into long-horizon places. | F23: Body | G23: KPD's design system uses the original site's quiet luxury behavior: large photography, measured typography, reduced ornament, editorial content bands, and a black menu system with direct navigation. Press & News | H23: 'Developing land logic into long-horizon places.' Supporting line: 'Large photography, measured typography, reduced ornament - design that holds its composure rather than asking for attention.' Button: Press & News. | I23: KPD press | K23: Informational | M23: Drafted | O23: 01-home.docx
A24: HOM-20 | B24: Home | C24: Home | D24: index.html | E24: Signals from the KPD platform. (id: news) | F24: Body | G24: Announcements, market observations, and development commentary are presented as a quiet editorial layer rather than a busy newsroom wall. BigGo Finance - Jun 30, 2026 | H24: 'Signals from the KPD platform - announcements, market observations and development commentary, presented as a quiet editorial layer.' | I24: Kasumigaseki news | K24: Informational | M24: Drafted | O24: 01-home.docx
A25: HOM-21 | B25: Home | C25: Home | D25: index.html | E25: Kasumigaseki Capital Acquires Hotel Development Land | F25: Body | G25: Kasumigaseki Capital announced the acquisition of approximately 17,300 square meters of land in Yamanakako Village for hotel development. Simply Wall St - Jun 2026 | H25: Keep as-is - structural (no copy change recommended). External headline; ensure link opens the source article (E-E-A-T). | K25: Informational | M25: Drafted | O25: 01-home.docx
A26: HOM-22 | B26: Home | C26: Home | D26: index.html | E26: Asian Growth Companies With High Insider Ownership | F26: Body | G26: Kasumigaseki Capital was noted among Asian growth companies, with Simply Wall St listing the real estate consulting business and market capitalization. BigGo Finance - Jun 25, 2026 | H26: Keep as-is - structural (no copy change recommended). External headline. | K26: Informational | M26: Drafted | O26: 01-home.docx
A27: HOM-23 | B27: Home | C27: Home | D27: index.html | E27: Kasumigaseki Capital: Notice Regarding Earthquake Impact | F27: Body | G27: Kasumigaseki Capital reported no confirmed damage to owned or managed facilities and no significant business impact at the time of disclosure. Events & Updates | H27: Keep as-is - structural (no copy change recommended). External headline. | K27: Informational | M27: Drafted | O27: 01-home.docx
A28: HOM-24 | B28: Home | C28: Home | D28: index.html | E28: Private previews and industry conversations. | F28: Body | G28: Events are now handled as editorial cards with direct inquiry routes. Dubai Media Office - May 10, 2026 | H28: 'Private previews and industry conversations - events handled as editorial cards with direct inquiry routes.' | K28: Informational | M28: Drafted | O28: 01-home.docx
A29: HOM-25 | B29: Home | C29: Home | D29: index.html | E29: Maktoum bin Mohammed Meets Founder of Kasumigaseki Capital | F29: Body | G29: The meeting with Hiroyuki Ogawa explored UAE growth, Dubai investment opportunities, and strategic partnerships. PROFILEmiami - Apr 6, 2026 | H29: Keep as-is - structural (no copy change recommended). External headline. | K29: Informational | M29: Drafted | O29: 01-home.docx
A30: HOM-26 | B30: Home | C30: Home | D30: index.html | E30: Kasumigaseki Capital Launches First U.S. Project | F30: Body | G30: Kasumigaseki Capital entered Miami and acquired Block C East at Miami Worldcenter for a mixed-use hotel and residential project. Yamaha - Feb 20, 2026 | H30: Keep as-is - structural (no copy change recommended). External headline. | K30: Informational | M30: Drafted | O30: 01-home.docx
A31: HOM-27 | B31: Home | C31: Home | D31: index.html | E31: Prestigious Dubai Projects: Restaurant and Real Estate Office | F31: Body | G31: Yamaha covered Kasumigaseki restaurant at Vida Emirates Hills and the KME Investment and Management office in Dubai Hills. | H31: Keep as-is - structural (no copy change recommended). External headline. | K31: Informational | M31: Drafted | O31: 01-home.docx
A32: HOM-28 | B32: Home | C32: Home | D32: index.html | E32: Stats band (id: investment) | F32: Stat band | G32: USD 5B+ — Parent platform assets under management. Tokyo — Listed institutional development heritage. Dubai — UAE development market focus. 3+ — Residential and hospitality-led pathways. (As of February, 2026) | H32: Numbers unchanged: USD 5B+ parent platform AUM / Tokyo - listed institutional heritage / Dubai - UAE market focus / 3+ residential and hospitality-led pathways. Add attribution line: 'Source: Kasumigaseki Capital, as of February 2026.' | K32: Informational | L32: How large is Kasumigaseki Capital? USD 5B+ AUM, TSE Prime listed (as of Feb 2026). | M32: Drafted | O32: 01-home.docx
A33: SXS-01 | B33: Developments | C33: Seven X Seven | D33: single-project.html | E33: Seven X Seven | F33: Body | H33: Hero title: 'Seven X Seven Residences'. Subtitle: 'Meydan Horizon, Dubai - a KPD development.' | I33: Seven X Seven Residences | J33: Meydan Horizon apartments for sale | K33: Commercial | L33: H1 keeps exact project + location keyword pairing. | M33: Drafted | O33: 02-seven-x-seven.docx
A34: SXS-02 | B34: Developments | C34: Seven X Seven | D34: single-project.html | E34: An address shaped by restraint (id: overview) | F34: Body | G34: Seven X Seven Residences sits within Meydan Horizon, planned around measured city access and the quiet rhythm of everyday living. The brief begins with how the home is used - arrival, light, and privacy - and lets the architecture follow. Explore Brochure | H34: Long copy - full rewrite in the page Doc (content/google-doc-templates/). | I34: Seven X Seven Residences Meydan | J34: Meydan Horizon Dubai apartment | K34: Commercial | L34: What is Seven X Seven Residences? First sentence: a residential development by KPD in Meydan Horizon designed around arrival, light and privacy. | M34: Drafted | O34: 02-seven-x-seven.docx
A35: SXS-03 | B35: Developments | C35: Seven X Seven | D35: single-project.html | E35: Meydan Horizon (id: meydan-horizon) | F35: Body | G35: Meydan Horizon places Seven X Seven within a measured urban district shaped by movement, water, and direct access to Dubai's business and cultural centers. The address gives residents a quieter daily rhythm while keeping Downtown, DIFC, DXB, and Ras Al Khor within practical reach. 10Min. Ras Al Khor 10Min. Downtown Dubai 10Min. DXB Airport | H35: 'Meydan Horizon places Seven X Seven within a measured urban district shaped by movement, water and direct access to Dubai's business and cultural centers - a quieter daily rhythm with Downtown, DIFC, DXB and Ras Al Khor in practical reach.' Stats kept: 10 min Ras Al Khor / 10 min Downtown / 10 min DXB. | I35: Meydan Horizon master plan | K35: Commercial | L35: How far is Seven X Seven from Downtown Dubai? About 10 minutes; DXB airport 10 minutes. | M35: Drafted | O35: 02-seven-x-seven.docx
A36: SXS-04 | B36: Developments | C36: Seven X Seven | D36: single-project.html | E36: Location (id: location) | F36: Body | G36: Set between Meydan, Ras Al Khor, and Downtown Dubai, Seven X Seven connects daily privacy with efficient access to work, leisure, aviation, and nature. Travel times are organized around the routes residents are most likely to use. 8 minsRas Al Khor Wildlife Sanctuary 13 minsDubai Design District 15 minsBusiness Bay 18 minsBurj Khalifa / Dubai Mall 20 minsDubai Hills Golf Club 25 minsBurj Al Arab 11 minsMeydan Grandstand and Racecourse 14 minsDubai Festival City Mall 14 minsDubai International Airport 16 minsDubai International Financial Centre 22 minsDubai Creek Golf and Yacht Club 42 minsPalm Jumeirah Seven X Seven 5 Minutes 10 Minutes 20 Minutes | H36: 'Set between Meydan, Ras Al Khor and Downtown Dubai, Seven X Seven connects daily privacy with efficient access to work, leisure, aviation and nature. Travel times are organized around the routes residents actually use.' Full travel-time list unchanged. | I36: Seven X Seven location | J36: distance Meydan to Downtown Dubai | K36: Commercial | L36: Distances answer PAA-style queries directly; keep as a definition list for snippet extraction. | M36: Drafted | O36: 02-seven-x-seven.docx
A37: SXS-05 | B37: Developments | C37: Seven X Seven | D37: single-project.html | E37: 3D Tour (id: showcase) | F37: Body | G37: Explore | H37: 'Explore the residence in three dimensions - arrival sequence, amenity floors and outlooks, walked at your own pace.' Button: Explore. | K37: Commercial | L37: Add VideoObject schema when 3D tour media is embedded. | M37: Drafted | O37: 02-seven-x-seven.docx
A38: SXS-06 | B38: Developments | C38: Seven X Seven | D38: single-project.html | E38: Amenities (id: amenities) | F38: Body | G38: Amenities are arranged as a quiet extension of the residence: water, wellness, lounge, landscape, and skyline moments working together rather than competing for attention. Amenity Sequence Residence Lounge Tower Profile Facade View Skyline View | H38: 'Amenities are arranged as a quiet extension of the residence - water, wellness, lounge, landscape and skyline moments working together rather than competing for attention.' Sequence kept: Amenity Sequence / Residence Lounge / Tower Profile / Facade View / Skyline View. | I38: Seven X Seven amenities | K38: Commercial | M38: Drafted | O38: 02-seven-x-seven.docx
A39: SXS-07 | B39: Developments | C39: Seven X Seven | D39: single-project.html | E39: Calm carried through every (id: brochure) | F39: Body | G39: From the pool edge to the tower envelope, the project favors softened light, composed materials, and outdoor rooms that let the city remain present without overwhelming the home. Brochure | H39: 'From the pool edge to the tower envelope, the project favors softened light, composed materials and outdoor rooms that let the city remain present without overwhelming the home. Finishes chosen once - and chosen to age well.' Button: Brochure. | I39: Seven X Seven brochure | K39: Commercial | M39: Drafted | O39: 02-seven-x-seven.docx
A40: SXS-08 | B40: Developments | C40: Seven X Seven | D40: single-project.html | E40: Floor Plans (id: floor-plans) | F40: Body | G40: Review indicative layouts designed around clear arrival, efficient circulation, privacy between rooms, and outdoor edges that extend everyday living. Type ADownload Type BDownload Type CDownload | H40: 'Indicative layouts designed around clear arrival, efficient circulation, privacy between rooms and outdoor edges that extend everyday living. Types A, B and C available to download.' | I40: Seven X Seven floor plan | K40: Commercial | L40: What floor plans does Seven X Seven offer? Types A, B, C - downloadable. | M40: Drafted | O40: 02-seven-x-seven.docx
A41: SXS-09 | B41: Developments | C41: Seven X Seven | D41: single-project.html | E41: Payment Plan (id: payment-plan) | F41: Body | G41: Payment milestones are structured for clarity across reservation, construction progress, completion, and post-handover settlement. Final percentages are confirmed during availability review. Download Payment Plan 10%On bookingReservation milestone and expression of intent. 40%During constructionStaged payments linked to development progress. 40%On completionBalance due at handover and title transfer. 10%After handoverOptional settlement window subject to offer terms. Enquire | H41: 'Payment milestones structured for clarity across reservation, construction, completion and post-handover settlement - reviewed with you as one complete cash-flow path. Final percentages confirmed during availability review.' Milestones unchanged: 10% booking / 40% construction / 40% completion / 10% post-handover. Button: Enquire. | I41: Seven X Seven payment plan | K41: Commercial | L41: What is the payment plan for Seven X Seven? 10/40/40/10 across booking, construction, completion, post-handover (indicative). | M41: Drafted | O41: 02-seven-x-seven.docx
A42: SXS-10 | B42: Developments | C42: Seven X Seven | D42: single-project.html | E42: Arrange a private viewing. | F42: CTA | G42: Floor plans, pricing, and availability are shared through a single appointment-led conversation. Book a viewing Register interest | H42: 'Arrange a private viewing. Floor plans, pricing and availability are shared through a single appointment-led conversation.' Buttons: Book a viewing / Register interest. | I42: Seven X Seven viewing | K42: Transactional | M42: Drafted | O42: 02-seven-x-seven.docx
A43: EVL-01 | B43: Developments | C43: Emerald Villa | D43: emerald-villa.html | E43: Emerald Villa | F43: Body | H43: Hero title: 'Emerald Villa'. Subtitle: 'A private garden villa in Dubai - a KPD development.' | I43: Emerald Villa Dubai | J43: private garden villa Dubai | K43: Commercial | L43: H1 keeps 'villa' + 'Dubai' pairing. | M43: Drafted | O43: 03-emerald-villa.docx
A44: EVL-02 | B44: Developments | C44: Emerald Villa | D44: emerald-villa.html | E44: A private rhythm held by landscape (id: overview) | F44: Body | G44: Emerald Villa is composed around privacy, garden arrival, and a softer rhythm of family-scaled spaces. The property balances a quiet residential mood with the clarity and discipline expected from a KPD development. Explore Brochure | H44: Long copy - full rewrite in the page Doc (content/google-doc-templates/). | I44: Emerald Villa Dubai | J44: garden villa Dubai family | K44: Commercial | L44: What is Emerald Villa? A garden-led private villa by KPD composed around planted arrival, layered privacy and family-scaled space. | M44: Drafted | O44: 03-emerald-villa.docx
A45: EVL-03 | B45: Developments | C45: Emerald Villa | D45: emerald-villa.html | E45: Garden-led privacy (id: garden-privacy) | F45: Body | G45: Emerald Villa is organized around planted arrival, private outdoor rooms, and a calm family rhythm. The address privileges stillness first, then connects that quiet setting to retail, schools, wellness, and the city's main business districts. 5Min. Daily retail 12Min. Schools 20Min. Downtown Dubai | H45: 'Emerald Villa is organized around planted arrival, private outdoor rooms and a calm family rhythm - stillness first, then retail, schools, wellness and the city's main business districts within reach.' Stats kept: 5 min daily retail / 12 min schools / 20 min Downtown. | I45: Emerald Villa location | K45: Commercial | L45: How far is Emerald Villa from Downtown Dubai? About 20 minutes. | M45: Drafted | O45: 03-emerald-villa.docx
A46: EVL-04 | B46: Developments | C46: Emerald Villa | D46: emerald-villa.html | E46: Location (id: location) | F46: Body | G46: Positioned for a private Dubai lifestyle, Emerald Villa connects garden-led residential calm with nearby retail, schools, wellness, and city access. 5 minsDaily retail and cafes 8 minsCommunity park 10 minsInternational schools 12 minsGolf and club house 15 minsBusiness Bay 20 minsDowntown Dubai 12 minsWellness and fitness clubs 18 minsDubai Mall 20 minsDubai International Airport 24 minsDubai Design District 28 minsPalm Jumeirah 35 minsAl Maktoum corridor Emerald Villa 5 Minutes 10 Minutes 20 Minutes | H46: 'Positioned for a private Dubai lifestyle, Emerald Villa connects garden-led residential calm with nearby retail, schools, wellness and city access.' Full travel-time list unchanged. | I46: Emerald Villa location | J46: villa near Downtown Dubai | K46: Commercial | M46: Drafted | O46: 03-emerald-villa.docx
A47: EVL-05 | B47: Developments | C47: Emerald Villa | D47: emerald-villa.html | E47: 3D Tour (id: showcase) | F47: Body | G47: Explore | H47: 'Explore the villa in three dimensions - garden arrival, living spaces and private suites.' Button: Explore. | K47: Commercial | M47: Drafted | O47: 03-emerald-villa.docx
A48: EVL-06 | B48: Developments | C48: Emerald Villa | D48: emerald-villa.html | E48: Amenities (id: amenities) | F48: Body | G48: Emerald Villa brings together private wellness, garden rooms, family gathering spaces, and hospitality cues to create a home that feels composed from arrival to retreat. Arrival Lobby Living Lounge Private Suite Kitchen Gallery Evening Living | H48: 'Emerald Villa brings together private wellness, garden rooms, family gathering spaces and hospitality cues - a home composed from arrival to retreat.' Sequence kept: Arrival Lobby / Living Lounge / Private Suite / Kitchen Gallery / Evening Living. | I48: Emerald Villa amenities | K48: Commercial | M48: Drafted | O48: 03-emerald-villa.docx
A49: EVL-07 | B49: Developments | C49: Emerald Villa | D49: emerald-villa.html | E49: Privacy held in the garden (id: brochure) | F49: Body | G49: The villa's living spaces are softened by planted edges, natural light, and outdoor rooms that make daily life feel protected without closing it off from the landscape. Brochure | H49: 'Living spaces are softened by planted edges, natural light and outdoor rooms that keep daily life protected without closing it off from the landscape. Materials chosen for how they age, not how they photograph.' Button: Brochure. | I49: Emerald Villa brochure | K49: Commercial | M49: Drafted | O49: 03-emerald-villa.docx
A50: EVL-08 | B50: Developments | C50: Emerald Villa | D50: emerald-villa.html | E50: Floor Plans (id: floor-plans) | F50: Body | G50: Indicative villa layouts prioritize arrival clarity, generous family gathering, private bedroom wings, and outdoor extensions that keep garden life close to the daily plan. Type ADownload Type BDownload Type CDownload | H50: 'Indicative villa layouts prioritize arrival clarity, generous family gathering, private bedroom wings and outdoor extensions that keep garden life close to the daily plan. Types A, B and C available to download.' | I50: Emerald Villa floor plan | K50: Commercial | M50: Drafted | O50: 03-emerald-villa.docx
A51: EVL-09 | B51: Developments | C51: Emerald Villa | D51: emerald-villa.html | E51: Payment Plan (id: payment-plan) | F51: Body | G51: Milestones are structured around reservation, progress, handover, and optional post-handover settlement, with final terms confirmed during availability review. Download Payment Plan 15%On bookingReservation and initial allocation milestone. 35%During constructionStaged payments aligned to project progress. 40%On completionBalance due at handover and transfer. 10%After handoverOptional settlement window subject to offer terms. Enquire | H51: 'Milestones structured around reservation, progress, handover and optional post-handover settlement, with final terms confirmed during availability review.' Milestones unchanged: 15% booking / 35% construction / 40% completion / 10% post-handover. Button: Enquire. | I51: Emerald Villa payment plan | K51: Commercial | L51: What is the payment plan for Emerald Villa? 15/35/40/10 (indicative). | M51: Drafted | O51: 03-emerald-villa.docx
A52: EVL-10 | B52: Developments | C52: Emerald Villa | D52: emerald-villa.html | E52: Arrange a private villa viewing. | F52: CTA | G52: Floor plans, pricing, and availability are shared through a single appointment-led conversation. Book a viewing Register interest | H52: 'Arrange a private villa viewing. Floor plans, pricing and availability are shared through a single appointment-led conversation.' Buttons: Book a viewing / Register interest. | K52: Transactional | M52: Drafted | O52: 03-emerald-villa.docx
A53: DHM-01 | B53: Developments | C53: Dubai Hills Mansion | D53: dubai-hills-mansion.html | E53: Dubai Hills Mansion | F53: Body | H53: Hero title: 'Dubai Hills Mansion'. Subtitle: 'A mansion-scale residence in Dubai Hills Estate - a KPD development.' | I53: Dubai Hills Mansion | J53: Dubai Hills Estate villa for sale | K53: Commercial | M53: Drafted | O53: 04-dubai-hills-mansion.docx
A54: DHM-02 | B54: Developments | C54: Dubai Hills Mansion | D54: dubai-hills-mansion.html | E54: Mansion living with quiet scale (id: overview) | F54: Body | G54: Dubai Hills Mansion is shaped for expansive family living, garden arrival, and a hospitality-led daily experience. The residence frames privacy, scale, and ease as one coherent property logic. Explore Brochure | H54: Long copy - full rewrite in the page Doc (content/google-doc-templates/). | I54: Dubai Hills Mansion | J54: mansion Dubai Hills Estate | K54: Commercial | L54: What is Dubai Hills Mansion? A mansion-scale KPD residence in Dubai Hills Estate shaped for expansive family living, garden arrival and private wellness. | M54: Drafted | O54: 04-dubai-hills-mansion.docx
A55: DHM-03 | B55: Developments | C55: Dubai Hills Mansion | D55: dubai-hills-mansion.html | E55: Dubai Hills Estate (id: dubai-hills-estate) | F55: Body | G55: Dubai Hills Mansion is positioned within a landscape-led district where golf, parks, retail, schools, and city access sit close to a private family address. The location gives the residence daily convenience without compromising the sense of scale and retreat. 5Min. Golf club 10Min. Dubai Hills Mall 20Min. Downtown Dubai | H55: 'Dubai Hills Mansion is positioned within a landscape-led district where golf, parks, retail, schools and city access sit close to a private family address - daily convenience without compromising scale and retreat.' Stats kept: 5 min golf / 10 min mall / 20 min Downtown. | I55: Dubai Hills Estate amenities | K55: Commercial | L55: How far is Dubai Hills Mansion from Downtown Dubai? About 20 minutes. | M55: Drafted | O55: 04-dubai-hills-mansion.docx
A56: DHM-04 | B56: Developments | C56: Dubai Hills Mansion | D56: dubai-hills-mansion.html | E56: Location (id: location) | F56: Body | G56: Located within Dubai Hills Estate, the mansion connects private residential scale with golf, retail, schools, parks, and direct city access. 5 minsDubai Hills Golf Club 7 minsCommunity parks 8 minsDubai Hills Mall 10 minsInternational schools 15 minsMall of the Emirates 18 minsBusiness Bay 12 minsHealthcare and wellness 20 minsDowntown Dubai 22 minsDubai Marina 25 minsDIFC 28 minsPalm Jumeirah 30 minsDubai International Airport Dubai Hills Mansion 5 Minutes 10 Minutes 20 Minutes | H56: 'Located within Dubai Hills Estate, the mansion connects private residential scale with golf, retail, schools, parks and direct city access.' Full travel-time list unchanged. | I56: Dubai Hills Estate location | K56: Commercial | M56: Drafted | O56: 04-dubai-hills-mansion.docx
A57: DHM-05 | B57: Developments | C57: Dubai Hills Mansion | D57: dubai-hills-mansion.html | E57: 3D Tour (id: showcase) | F57: Body | G57: Explore | H57: 'Explore the mansion in three dimensions - garden arrival, entertaining floors and private wings.' Button: Explore. | K57: Commercial | M57: Drafted | O57: 04-dubai-hills-mansion.docx
A58: DHM-06 | B58: Developments | C58: Dubai Hills Mansion | D58: dubai-hills-mansion.html | E58: Amenities (id: amenities) | F58: Body | G58: Dubai Hills Mansion brings together generous indoor rooms, private outdoor amenities, wellness spaces, and family-focused landscape moments within a mansion-scale setting. Wellness Bath Evening Bedroom Chef Kitchen Garden Living Landscape Arrival | H58: 'Generous indoor rooms, private outdoor amenities, wellness spaces and family-focused landscape moments within a mansion-scale setting - composed rather than oversized.' Sequence kept: Wellness Bath / Evening Bedroom / Chef Kitchen / Garden Living / Landscape Arrival. | I58: Dubai Hills Mansion amenities | K58: Commercial | M58: Drafted | O58: 04-dubai-hills-mansion.docx
A59: DHM-07 | B59: Developments | C59: Dubai Hills Mansion | D59: dubai-hills-mansion.html | E59: Scale softened by landscape (id: brochure) | F59: Body | G59: The mansion's generous rooms are balanced by garden views, shaded edges, and warm interior surfaces, creating a residence that feels composed rather than oversized. Brochure | H59: 'The mansion's generous rooms are balanced by garden views, shaded edges and warm interior surfaces. Scale softened by landscape; presence earned by restraint.' Button: Brochure. | I59: Dubai Hills Mansion brochure | K59: Commercial | M59: Drafted | O59: 04-dubai-hills-mansion.docx
A60: DHM-08 | B60: Developments | C60: Dubai Hills Mansion | D60: dubai-hills-mansion.html | E60: Floor Plans (id: floor-plans) | F60: Body | G60: Indicative mansion layouts organize arrival, entertaining, family privacy, guest accommodation, and outdoor living into a clear residential sequence. Type ADownload Type BDownload Type CDownload | H60: 'Indicative mansion layouts organize arrival, entertaining, family privacy, guest accommodation and outdoor living into a clear residential sequence. Types A, B and C available to download.' | I60: Dubai Hills Mansion floor plan | K60: Commercial | M60: Drafted | O60: 04-dubai-hills-mansion.docx
A61: DHM-09 | B61: Developments | C61: Dubai Hills Mansion | D61: dubai-hills-mansion.html | E61: Payment Plan (id: payment-plan) | F61: Body | G61: Milestones are structured around reservation, progress, handover, and optional post-handover settlement, with final terms confirmed during availability review. Download Payment Plan 15%On bookingReservation and initial allocation milestone. 35%During constructionStaged payments aligned to project progress. 40%On completionBalance due at handover and transfer. 10%After handoverOptional settlement window subject to offer terms. Enquire | H61: 'Milestones structured around reservation, progress, handover and optional post-handover settlement, with final terms confirmed during availability review.' Milestones unchanged: 15% booking / 35% construction / 40% completion / 10% post-handover. Button: Enquire. | I61: Dubai Hills Mansion payment plan | K61: Commercial | L61: What is the payment plan for Dubai Hills Mansion? 15/35/40/10 (indicative). | M61: Drafted | O61: 04-dubai-hills-mansion.docx
A62: DHM-10 | B62: Developments | C62: Dubai Hills Mansion | D62: dubai-hills-mansion.html | E62: Arrange a private mansion viewing. | F62: CTA | G62: Floor plans, pricing, and availability are shared through a single appointment-led conversation. Book a viewing Register interest | H62: 'Arrange a private mansion viewing. Floor plans, pricing and availability are shared through a single appointment-led conversation.' Buttons: Book a viewing / Register interest. | K62: Transactional | M62: Drafted | O62: 04-dubai-hills-mansion.docx
A63: ABO-01 | B63: About | C63: About Us | D63: about-us.html | E63: Hero — 'Soulful Places / Enriched Lives' | F63: Hero | G63: Kicker: 'About'. H1: 'Soulful Places / Enriched Lives'. Intro: 'Kasumigaseki Properties Development brings institutional discipline, long-term capital, and a decades-deep development track record into one of the world's most dynamic property markets.' | H63: Kicker: 'About'. H1 kept: 'Soulful Places / Enriched Lives'. Intro: 'Kasumigaseki Properties Development (KPD) is the Dubai real estate arm of Kasumigaseki Capital, a group listed on the Tokyo Stock Exchange Prime Market - bringing institutional discipline, long-term capital and a decades-deep development track record to the UAE.' | I63: Kasumigaseki Properties Development | J63: Japanese property developer Dubai | K63: Informational | L63: Who owns KPD? Kasumigaseki Capital, TSE Prime listed. Stated in hero intro. | M63: Drafted | O63: 05-about-us.docx
A64: ABO-02 | B64: About | C64: About Us | D64: about-us.html | E64: Story (id: about) — 'Soulful Places / Enriched Lives' | F64: Body | G64: Kasumigaseki Properties Development brings the institutional discipline of Kasumigaseki Capital into Dubai's residential market, translating a global platform of development, hospitality, logistics, healthcare, and fund-management experience into a focused UAE pipeline. Established to extend that legacy into one of the world's most dynamic property markets, KPD brings institutional discipline, long-term capital, and a decades-deep development track record to the UAE - delivering projects built not just for today's market, but for generations ahead. | H64: Long copy - full rewrite in the page Doc (content/google-doc-templates/). | I64: about Kasumigaseki Properties Development | K64: Informational | L64: What is KPD's story? Japanese philosophy + institutional capital applied to Dubai residential development. | M64: Drafted | O64: 05-about-us.docx
A65: ABO-03 | B65: About | C65: About Us | D65: about-us.html | E65: Our Mission (id: mission) | F65: Body | G65: Our mission is to create residential, hospitality, and mixed-use destinations with disciplined feasibility, thoughtful architecture, and delivery control. We shape communities that elevate daily living while protecting long-term value for partners, buyers, and the city around them. | H65: 'Our mission is purposeful progress: to bring Japanese sophistication and intelligence to every challenge - meticulous in detail, deliberate in design, unwavering in standard, regardless of project, price point or community. We build where we are needed most.' | K65: Informational | M65: Drafted | O65: 05-about-us.docx
A66: ABO-04 | B66: About | C66: About Us | D66: about-us.html | E66: Our Vision (id: mission) | F66: Body | G66: Our vision is to become a trusted boutique development platform for the region, where every project is guided by clarity, restraint, and durable performance. We aim to create places that feel precise, enduring, commercially sound, and unmistakably considered. | H66: 'Our vision is to better the cities and communities we build within - turning real challenges into liveable, long-lasting solutions through innovation, craft, care and guardianship, for this country, its people and the generations after them.' | K66: Informational | M66: Drafted | O66: 05-about-us.docx
A67: ABO-05 | B67: About | C67: About Us | D67: about-us.html | E67: Chairman (id: chairman) — Mohammed Alabbar | F67: Body | G67: Quote: 'The markets we operate in reward patience, clarity, and disciplined execution. KPD was formed to bring those qualities into development decisions, from how land is assessed to how a finished place will be lived in, operated, and valued over time. Our work is measured by the confidence of our partners, the quality of our delivery, and the long-term relevance of the communities and assets we help create.' Signature: Mohammed Alabbar — Chairman. | H67: Quote kept with light polish: 'The markets we operate in reward patience, clarity and disciplined execution. KPD was formed to bring those qualities into development decisions - from how land is assessed to how a finished place will be lived in, operated and valued over time. Our work is measured by the confidence of our partners, the quality of our delivery, and the long-term relevance of the communities we help create.' Signature: Mohammed Alabbar - Chairman. | K67: Informational | L67: Note: executive quote - final wording to be approved by client/office. | M67: Drafted | O67: 05-about-us.docx
A68: ABO-06 | B68: About | C68: About Us | D68: about-us.html | E68: CEO (id: ceo) — Mohammed Alabbar | F68: Body | G68: Same quote as Chairman block. | H68: Proposed distinct CEO block (replaces duplicate Chairman quote): 'Dubai rewards developers who arrive with patience and leave with a reputation. KPD was built to do both - to assess land with discipline, to build with craft, and to remain responsible for what we hand over long after the keys change hands.' Signature: [CEO name] - Chief Executive Officer. | K68: Informational | L68: CLIENT DECISION: delivered site repeats the Chairman quote here, signed 'CEO'. Recommend confirming the CEO name/quote or removing the block. | M68: Drafted | O68: 05-about-us.docx | P68: Delivered file repeats the Chairman quote here, signed 'CEO'.
A69: ABO-07 | B69: About | C69: About Us | D69: about-us.html | E69: Executive Management — Hiroyuki Chiba | F69: Body | G69: Role: Executive Director. Bio: 'Hiroyuki Chiba supports KPD's long-term development philosophy, connecting institutional capital discipline with projects designed for durable value, memorable placemaking, and partner confidence.' | H69: Role: Executive Director. Bio: 'Hiroyuki Chiba connects institutional capital discipline with projects designed for durable value, memorable placemaking and partner confidence - the quiet standard behind every KPD development.' | K69: Informational | M69: Drafted | O69: 05-about-us.docx
A70: ABO-08 | B70: About | C70: About Us | D70: about-us.html | E70: Executive Management — Ammar Al Tamimi | F70: Body | G70: Role: Development Director. Bio: 'The executive management team supports the company's development platform through disciplined feasibility, delivery control, design coordination, and market positioning across every KPD project.' | H70: Role: Development Director. Bio: 'Ammar Al Tamimi leads delivery across the KPD platform - disciplined feasibility, delivery control, design coordination and market positioning, from first site study to handover.' | K70: Informational | M70: Drafted | O70: 05-about-us.docx
A71: ABO-09 | B71: About | C71: About Us | D71: about-us.html | E71: Executive Management — Anas Al Khatib | F71: Body | G71: Role: Commercial Director. Bio: 'KPD leadership brings together real estate judgment, capital planning, and operational clarity to create places that remain commercially sound and emotionally resonant over time.' | H71: Role: Commercial Director. Bio: 'Anas Al Khatib brings together real estate judgment, capital planning and operational clarity - places that remain commercially sound and emotionally resonant over time.' | K71: Informational | M71: Drafted | O71: 05-about-us.docx
A72: LEG-01 | B72: About | C72: Legacy (Our Legacy) | D72: legacy.html | E72: Hero (id: top) | F72: Hero | G72: Kicker: 'Legacy'. H1: 'A long-horizon platform'. Intro: 'From Tokyo to Dubai, the KPD platform is shaped by disciplined capital, measured execution, and development value built to hold over time.' | H72: Kicker: 'Legacy'. H1 kept: 'A long-horizon platform'. Intro: 'From Tokyo to Dubai - the KPD platform is shaped by disciplined capital, measured execution and development value built to hold over time.' | I72: Kasumigaseki Capital track record | K72: Informational | M72: Drafted | O72: 06-legacy.docx
A73: LEG-02 | B73: About | C73: Legacy (Our Legacy) | D73: legacy.html | E73: Timeline 2014 — Foundations of the platform | F73: Timeline | G73: The early phase centered on site logic, underwriting rigor, and a belief that every design decision should begin with commercial clarity. The first chapter was less about scale and more about method. Opportunity screening, demand discipline, and feasibility-led thinking became the base layer for how the platform would evaluate, prioritize, and shape future developments. | H73: Long copy - full rewrite in the page Doc (content/google-doc-templates/). | K73: Informational | M73: Drafted | O73: 06-legacy.docx | P73: Expandable timeline item.
A74: LEG-03 | B74: About | C74: Legacy (Our Legacy) | D74: legacy.html | E74: Timeline 2016 — Boutique residential focus sharpens | F74: Timeline | G74: Early residential briefs helped define a clearer position around privacy, livability, and product quality over volume-driven development. The residential lens matured into a stronger product philosophy. Layout efficiency, calm arrival experiences, and long-term habitability started to influence how the platform translated commercial strategy into the language of everyday living. | H74: Long copy - full rewrite in the page Doc (content/google-doc-templates/). | K74: Informational | M74: Drafted | O74: 06-legacy.docx | P74: Expandable timeline item.
A75: LEG-04 | B75: About | C75: Legacy (Our Legacy) | D75: legacy.html | E75: Timeline 2018 — Hospitality and mixed-use capability expands | F75: Timeline | G75: The platform broadened beyond one asset type, bringing placemaking, operational thinking, and return discipline into a wider development model. Hospitality and mixed-use opportunities introduced a richer operating layer. The development story now had to hold together brand, user flow, public realm, and asset performance in one cohesive strategy rather than as separate conversations. | H75: Long copy - full rewrite in the page Doc (content/google-doc-templates/). | K75: Informational | M75: Drafted | O75: 06-legacy.docx | P75: Expandable timeline item.
A76: LEG-05 | B76: About | C76: Legacy (Our Legacy) | D76: legacy.html | E76: Timeline 2020 — Execution systems become more deliberate | F76: Timeline | G76: Consultant alignment, delivery governance, and budget coordination matured into a more controlled framework for moving from concept to handover. This phase deepened the platform's delivery confidence. Programme logic, cost control, design decision-making, and handover preparedness were treated as a single operating system rather than isolated workstreams. | H76: Long copy - full rewrite in the page Doc (content/google-doc-templates/). | K76: Informational | M76: Drafted | O76: 06-legacy.docx | P76: Expandable timeline item.
A77: LEG-06 | B77: About | C77: Legacy (Our Legacy) | D77: legacy.html | E77: Timeline 2023 — Regional ambition takes a clearer shape | F77: Timeline | G77: A stronger Middle East lens sharpened the platform's opportunity selection around urban demand, investor confidence, and resilient end-user value. The legacy was no longer just operational; it became directional. Market selection, product timing, and the balance between identity and commercial logic began to point more clearly toward a refined regional platform and a sharper development voice. | H77: Long copy - full rewrite in the page Doc (content/google-doc-templates/). | K77: Informational | M77: Drafted | O77: 06-legacy.docx | P77: Expandable timeline item.
A78: LEG-07 | B78: About | C78: Legacy (Our Legacy) | D78: legacy.html | E78: Timeline 2026 — Emerald Villa marks the current chapter | F78: Timeline | G78: The present expression of the legacy is more focused: boutique scale, stronger identity, and developments shaped for enduring value rather than short-lived momentum. The current moment shows a more distilled version of the story. Projects like Emerald Villa and Dubai Hills Mansion reflect the platform's move toward precise scale, elevated livability, and a development process that remains calm, commercially grounded, and durable by design. | H78: Long copy - full rewrite in the page Doc (content/google-doc-templates/). | K78: Informational | M78: Drafted | O78: 06-legacy.docx | P78: Expandable timeline item.
A79: MED-01 | B79: Media (News) | C79: News & Updates | D79: news.html | E79: Hero (id: top) | F79: Hero | G79: Kicker: 'Media'. H1: 'News and updates'. Intro: 'Announcements, market observations, and development commentary from Kasumigaseki Properties Development.' | H79: Kicker: 'Media'. H1: 'News and updates'. Intro: 'Announcements, market observations and development commentary from Kasumigaseki Properties Development.' | I79: Dubai real estate news | J79: Kasumigaseki news | K79: Informational | M79: Drafted | O79: 07-news-updates.docx
A80: MED-02 | B80: Media (News) | C80: News & Updates | D80: news.html | E80: Filter tabs (id: updates) | F80: Form | G80: All | News (default) | Blogs Toggles the News live feed vs the Blogs grid below. | H80: Keep as-is - structural (no copy change recommended). Filter labels All / News / Blogs stay; ensure tab state is URL-addressable (?tab=news) in Phase 2 for crawlability. | K80: Navigational | M80: Drafted | O80: 07-news-updates.docx
A81: MED-03 | B81: Media (News) | C81: News & Updates | D81: news.html | E81: News tab — live feed | F81: Body | G81: BigGo Finance - Jun 30, 2026 — Kasumigaseki Capital Acquires Hotel Development Land: Kasumigaseki Capital announced the acquisition of approximately 17,300 square meters of land in Yamanakako Village for hotel development. Simply Wall St - Jun 2026 — Asian Growth Companies With High Insider Ownership: Kasumigaseki Capital was noted among Asian growth companies, with Simply Wall St listing the real estate consulting business and market capitalization. BigGo Finance - Jun 25, 2026 — Kasumigaseki Capital: Notice Regarding Earthquake Impact: Kasumigaseki Capital reported no confirmed damage to owned or managed facilities and no significant business impact at the time of disclosure. Dubai Media Office - May 10, 2026 — Maktoum bin Mohammed Meets Founder of Kasumigaseki Capital: The meeting with Hiroyuki Ogawa explored UAE growth, Dubai investment opportunities, and strategic partnerships. PROFILEmiami - Apr 6, 2026 — Kasumigaseki Capital Launches First U.S. Project: Kasumigaseki Capital entered Miami and acquired Block C East at Miami Worldcenter for a mixed-use hotel and residential project. Yamaha - Feb 20, 2026 — Prestigious Dubai Projects: Restaurant and Real Estate Office: Yamaha covered Kasumigaseki restaurant at Vida Emirates Hills and the KME Investment and Management office in Dubai Hills. | H81: Keep as-is - structural (no copy change recommended). Live feed items are external coverage. Ensure outbound links carry rel='noopener' and source names (E-E-A-T). | K81: Informational | M81: Drafted | O81: 07-news-updates.docx | P81: Loaded at runtime from assets/data/live-news-cache.json (script assets/js/live-news.js); reloaded via 'Refresh Feed'.
A82: MED-04 | B82: Media (News) | C82: News & Updates | D82: news.html | E82: Blogs tab — blog cards | F82: Body | G82: Land Logic Before Form: Why site constraints, arrival, frontage, and address behavior shape the earliest development decisions. What Makes Yield Durable: A note on rental readiness, service-charge discipline, and product features that remain relevant beyond launch. Quiet Architecture: How restraint, material clarity, and practical operations can create a stronger residential experience. | H82: Blog card summaries tightened: 'Land Logic Before Form - why site constraints, arrival, frontage and address behavior shape the earliest development decisions.' / 'What Makes Yield Durable - rental readiness, service-charge discipline and product features that stay relevant beyond launch.' / 'Quiet Architecture - how restraint, material clarity and practical operations build a stronger residential experience.' | I82: Dubai real estate blog | K82: Informational | M82: Drafted | O82: 07-news-updates.docx | P82: Links to blog-article.html?article=<slug>.
A83: MED-05 | B83: Media (News) | C83: News & Updates | D83: news.html | E83: Loading/empty states | F83: Body | G83: Status line: 'Loading live articles from the internet...' Empty state: 'Live coverage could not be loaded right now. Please refresh the feed or try again shortly.' | H83: Status: 'Loading live articles from the internet...' Empty state: 'Live coverage could not be loaded right now. Please refresh the feed or try again shortly.' (kept - functional copy). | K83: Informational | M83: Drafted | O83: 07-news-updates.docx
A84: BLG-01 | B84: Media (News) | C84: Blog Article (template) | D84: blog-article.html | E84: Template structure | F84: Template | G84: Page shell populated from assets/js/articles.js (Blog bucket) via ?article=<slug>. Elements: type label ('Blog'), date label, H1 title, summary, cover image (body paragraphs from article data). Actions: 'Back to Blogs' (news.html#updates), 'Contact KPD' (contact.html). | H84: Template note: add JSON-LD BlogPosting + Article schema per article; H1 = article title; type label 'Blog'. | K84: Informational | M84: Drafted | O84: 08-articles.docx | P84: No content in HTML itself; all text is injected by JS.
A85: BLG-02 | B85: Media (News) | C85: Blog Article (template) | D85: blog-article.html | E85: Article — Land Logic Before Form (land-logic-before-form) | F85: Body | G85: Type: Blog | Date: Market Notes Summary: Why site constraints, arrival, frontage, and address behavior shape the earliest development decisions. Body: Every durable project begins before architecture. It starts with land logic: what a site allows, what it resists, how it is approached, and how its edges will be read over time. Frontage, visibility, service access, arrival rhythm, and surrounding movement patterns all influence the kind of product a site can support. Treating those inputs carefully gives a project its first layer of discipline. When form follows that logic, the architecture has a clearer job. It does not need to compensate for weak positioning; it can refine a proposition that already understands its place. | H85: Long copy - full rewrite in the page Doc (content/google-doc-templates/). | I85: land logic real estate development | K85: Informational | L85: Why does site analysis come before design? Answered in first paragraph. | M85: Drafted | O85: 08-articles.docx | P85: Replaces template placeholders when opened.
A86: BLG-03 | B86: Media (News) | C86: Blog Article (template) | D86: blog-article.html | E86: Article — What Makes Yield Durable (what-makes-yield-durable) | F86: Body | G86: Type: Blog | Date: Investor Lens Summary: A note on rental readiness, service-charge discipline, and product features that remain relevant beyond launch. Body: Yield durability is rarely created by one headline number. It is built through a sequence of small decisions that make a property easy to understand, easy to operate, and easy to live in. Rental readiness depends on product clarity, furnishing logic, maintenance discipline, and amenities that support real routines rather than marketing lists. Service-charge control matters because it protects the net experience for owners and tenants alike. The strongest projects remain legible after launch. They offer a clear reason to be chosen again, not just a reason to be noticed once. | H86: Long copy - full rewrite in the page Doc (content/google-doc-templates/). | I86: durable rental yield Dubai | K86: Informational | L86: What makes a rental yield durable? Answered in first paragraph. | M86: Drafted | O86: 08-articles.docx | P86: Replaces template placeholders when opened.
A87: BLG-04 | B87: Media (News) | C87: Blog Article (template) | D87: blog-article.html | E87: Article — Quiet Architecture (quiet-architecture) | F87: Body | G87: Type: Blog | Date: Design Notes Summary: How restraint, material clarity, and practical operations can create a stronger residential experience. Body: Quiet architecture does not mean passive architecture. It means design that knows when to hold back, when to frame, and when to let daily life take priority. In residential development, restraint can be a form of confidence. Clear materials, controlled light, practical circulation, and durable details often create a stronger experience than excessive visual noise. For KPD, the aim is not to make buildings that shout at first glance. It is to make places that continue to feel considered after years of use. | H87: Long copy - full rewrite in the page Doc (content/google-doc-templates/). | I87: quiet architecture design | K87: Informational | L87: What is quiet architecture? Answered in first paragraph. | M87: Drafted | O87: 08-articles.docx | P87: Replaces template placeholders when opened.
A88: NAR-01 | B88: Media (News) | C88: News Article (template) | D88: news-article.html | E88: Template structure | F88: Template | G88: News equivalent of the blog template (data-article-kind='news'): type label ('News'), date label, H1 title, summary, cover image, body paragraphs. Populated from assets/js/articles.js (News bucket) via ?article=<slug>. | H88: Template note: add NewsArticle JSON-LD; H1 = article title; type label 'News'. | K88: Informational | M88: Drafted | O88: 08-articles.docx | P88: No content in HTML itself; all text is injected by JS.
A89: NAR-02 | B89: Media (News) | C89: News Article (template) | D89: news-article.html | E89: Article — Design, Underwriting & Endurance Forum (design-underwriting-endurance) | F89: Body | G89: Type: News | Date: June 10, 2026 Summary: A closed-room discussion on land logic, delivery discipline, design intent, and how long-horizon value is protected before a project reaches market. Body: KPD convened a focused forum around the relationship between design, underwriting, and long-term project relevance. The conversation centered on how early feasibility decisions shape every later layer of a development, from frontage and arrival to operations, maintenance, leasing, and resale confidence. The session treated design as a commercial discipline rather than a decorative layer. Participants discussed why enduring residential value depends on a project being clear about its audience, its service logic, its public edges, and the daily routines it supports. For KPD, this is where development begins: with the patience to test assumptions, the restraint to avoid unnecessary complexity, and the discipline to make places that remain useful and memorable beyond launch. | H89: Long copy - full rewrite in the page Doc (content/google-doc-templates/). | I89: real estate underwriting forum Dubai | K89: Informational | M89: Drafted | O89: 08-articles.docx | P89: Replaces template placeholders when opened.
A90: NAR-03 | B90: Media (News) | C90: News Article (template) | D90: news-article.html | E90: Article — Seven X Seven: A Denser Urban Brief (seven-x-seven-project-note) | F90: Body | G90: Type: News | Date: Project Note Summary: A sharper urban mixed-use brief built around positioning, movement, and future delivery logic. Body: Seven X Seven is shaped around an urban reading of density, frontage, and movement. The project is positioned to make its address, arrival sequence, and residential experience feel coherent from the street to the private interior. Rather than relying on scale alone, the project uses measured facade rhythm, amenity logic, and material restraint to create a residential experience that is composed and commercially legible. The development reflects KPD's wider approach: every spatial decision should carry operational, experiential, and long-term value. | H90: Long copy - full rewrite in the page Doc (content/google-doc-templates/). | I90: Seven X Seven project | K90: Commercial | M90: Drafted | O90: 08-articles.docx | P90: Replaces template placeholders when opened.
A91: NAR-04 | B91: Media (News) | C91: News Article (template) | D91: news-article.html | E91: Article — Emerald Villa Private Preview (emerald-villa-private-preview) | F91: Body | G91: Type: News | Date: May 22, 2026 Summary: An invitation-only preview of Emerald Villa's planning, amenity story, and garden-led residential experience. Body: Emerald Villa was presented through a private preview focused on the relationship between arrival, landscape, privacy, and interior calm. The walkthrough introduced the project as a residential environment shaped for family-scaled living and long-horizon ownership. The preview highlighted the role of garden rooms, shaded outdoor areas, and warm interior materiality in creating a home that feels generous without becoming performative. KPD's team framed the project as a quieter expression of luxury: one built around clarity, daily use, and a composed sense of permanence. | H91: Long copy - full rewrite in the page Doc (content/google-doc-templates/). | I91: Emerald Villa preview | K91: Commercial | M91: Drafted | O91: 08-articles.docx | P91: Replaces template placeholders when opened.
A92: INV-01 | B92: Media (Investor Guide) | C92: Invest in Dubai | D92: invest-in-dubai.html | E92: Long-horizon value in Dubai | F92: Body | G92: A focused investment pathway for buyers seeking regulated ownership, composed residential assets, and advisory clarity across Dubai's next chapter. Global Capital access Dubai Freehold market KPD Disciplined delivery | H92: 'Long-horizon value in Dubai. A focused investment pathway for buyers seeking regulated ownership, composed residential assets and advisory clarity across Dubai's next chapter.' Chips kept: Global - capital access / Dubai - freehold market / KPD - disciplined delivery. | I92: invest in Dubai real estate | J92: Dubai property investment | K92: Commercial | L92: Is Dubai real estate a good investment? Intro answers: regulated freehold market, rental demand, institutional-grade advisory. | M92: Drafted | O92: 09-invest-in-dubai.docx
A93: INV-02 | B93: Media (Investor Guide) | C93: Invest in Dubai | D93: invest-in-dubai.html | E93: Why Dubai remains investable | F93: Body | G93: Quick answers to the core motivations behind Dubai investment: regulated ownership, business mobility, rental demand, and a city that continues to attract global residents and capital. | H93: 'Why Dubai remains investable - quick answers to the core motivations behind Dubai investment: regulated ownership, business mobility, rental demand and a city that continues to attract global residents and capital.' | I93: why invest in Dubai property | K93: Informational | M93: Drafted | O93: 09-invest-in-dubai.docx
A94: INV-03 | B94: Media (Investor Guide) | C94: Invest in Dubai | D94: invest-in-dubai.html | E94: Government-backed market | F94: Body | G94: Clear title registration, regulated escrow, and defined transaction steps give international buyers a visible framework for decision-making. | H94: 'A government-backed market: clear title registration, regulated escrow and defined transaction steps give international buyers a visible framework for decision-making.' | I94: Dubai freehold ownership rules | K94: Informational | L94: Is property ownership in Dubai regulated? Yes - title registration + escrow framework. | M94: Drafted | O94: 09-invest-in-dubai.docx
A95: INV-04 | B95: Media (Investor Guide) | C95: Invest in Dubai | D95: invest-in-dubai.html | E95: Capital growth | F95: Body | G95: Prime Dubai districts continue to benefit from population growth, infrastructure investment, and sustained end-user demand. | H95: 'Capital growth: prime Dubai districts continue to benefit from population growth, infrastructure investment and sustained end-user demand.' | I95: Dubai property price growth | K95: Informational | M95: Drafted | O95: 09-invest-in-dubai.docx
A96: INV-05 | B96: Media (Investor Guide) | C96: Invest in Dubai | D96: invest-in-dubai.html | E96: World-class safety | F96: Body | G96: Governance, security, infrastructure, and daily quality of life support Dubai's appeal for families, entrepreneurs, and global residents. | H96: 'World-class safety: governance, security, infrastructure and daily quality of life support Dubai's appeal for families, entrepreneurs and global residents.' | I96: living in Dubai safety | K96: Informational | M96: Drafted | O96: 09-invest-in-dubai.docx
A97: INV-06 | B97: Media (Investor Guide) | C97: Invest in Dubai | D97: invest-in-dubai.html | E97: Rental yield depth | F97: Body | G97: Leasing demand is supported by business relocation, international mobility, tourism, schools, and a growing base of long-term residents. | H97: 'Rental yield depth: leasing demand is supported by business relocation, international mobility, tourism, schools and a growing base of long-term residents.' | I97: Dubai rental yields | K97: Informational | L97: What rental yield can Dubai offer? See comparison table below (approx. 7.5% gross in prime areas). | M97: Drafted | O97: 09-invest-in-dubai.docx
A98: INV-07 | B98: Media (Investor Guide) | C98: Invest in Dubai | D98: invest-in-dubai.html | E98: Transparent process | F98: Body | G98: Buyers can evaluate fees, documents, ownership route, payment milestones, and handover obligations before committing. | H98: 'A transparent process: fees, documents, ownership route, payment milestones and handover obligations can all be evaluated before committing.' | I98: buying property in Dubai process | K98: Informational | M98: Drafted | O98: 09-invest-in-dubai.docx
A99: INV-08 | B99: Media (Investor Guide) | C99: Invest in Dubai | D99: invest-in-dubai.html | E99: Flexible entry options | F99: Body | G99: Off-plan and ready homes create different routes for investors reviewing cash flow, handover timing, and portfolio balance. | H99: 'Flexible entry options: off-plan and ready homes create different routes for investors reviewing cash flow, handover timing and portfolio balance.' | I99: off-plan vs ready property Dubai | K99: Commercial | M99: Drafted | O99: 09-invest-in-dubai.docx
A100: INV-09 | B100: Media (Investor Guide) | C100: Invest in Dubai | D100: invest-in-dubai.html | E100: Global mobility | F100: Body | G100: Residency pathways, aviation connectivity, and a pro-business environment make Dubai a practical base as well as an investment market. | H100: 'Global mobility: residency pathways, aviation connectivity and a pro-business environment make Dubai a practical base as well as an investment market.' | I100: Dubai residency by property | K100: Commercial | M100: Drafted | O100: 09-invest-in-dubai.docx
...

Sheet Page SEO
A1: Page | B1: ID | C1: Current URL (legacy) | D1: Future route (suggested) | E1: Current meta title | F1: Current meta description | G1: Current H1 | H1: Proposed meta title (<=60 chars) | I1: Proposed meta description (<=155 chars) | J1: Target keyword | K1: Suggested schema | L1: Voice/positioning note (from deck) | M1: Status | N1: Doc link
A2: Home | B2: HOM | C2: /legacy/index.html | D2: / | E2: Kasumigaseki Properties Development | F2: Kasumigaseki Properties Development creates disciplined, long-horizon real estate destinations in Dubai. | G2: Turning Challenge Into Value | H2: KPD | Japanese-Backed Property Developer in Dubai | I2: Kasumigaseki Properties Development (KPD) builds Dubai residences with Tokyo-listed discipline: long-term capital, Japanese craft, value for generations. | J2: Dubai property developer | K2: Organization, WebSite | L2: Calm, certain, considered. Lead with 'Turning challenge into value'; evidence over adjectives (TSE Prime, AUM figures); Japanese discipline as governance, not aesthetic. Taglines available: 'The art of knowing', 'Think forward'. | M2: Drafted | N2: 01-home.docx
A3: Seven X Seven | B3: SXS | C3: /legacy/single-project.html | D3: /developments/seven-x-seven | E3: Seven X Seven | Kasumigaseki Properties Development | F3: Explore Seven X Seven by Kasumigaseki Properties Development: soulful places, amenities, location, and project enquiry. | G3: Seven X Seven | H3: Seven X Seven Residences | Meydan Horizon, Dubai | I3: Seven X Seven Residences in Meydan Horizon: a composed KPD address shaped by arrival, light and privacy, 10 minutes from Downtown Dubai. | J3: Seven X Seven Residences | K3: RealEstateListing, VideoObject, BreadcrumbList | L3: Restraint as luxury. Fact-first (travel times, payment milestones); quiet authority; no amenity-listing hype - amenities 'work together rather than compete'. | M3: Drafted | N3: 02-seven-x-seven.docx
A4: Emerald Villa | B4: EVL | C4: /legacy/emerald-villa.html | D4: /developments/emerald-villa | E4: Emerald Villa | Kasumigaseki Properties Development | F4: Explore Emerald Villa by Kasumigaseki Properties Development: private garden living, wellness amenities, location, and project enquiry. | G4: Emerald Villa | H4: Emerald Villa | Private Garden Villas in Dubai | I4: Emerald Villa by KPD: garden-led private villa living in Dubai with planted arrival, layered privacy and family-scaled spaces. Book a private viewing. | J4: Emerald Villa Dubai | K4: RealEstateListing, VideoObject, BreadcrumbList | L4: Garden-led privacy vocabulary: planted arrival, stillness, protection without isolation. Family-scale warmth, Anshin undertone. | M4: Drafted | N4: 03-emerald-villa.docx
A5: Dubai Hills Mansion | B5: DHM | C5: /legacy/dubai-hills-mansion.html | D5: /developments/dubai-hills-mansion | E5: Dubai Hills Mansion | Kasumigaseki Properties Development | F5: Explore Dubai Hills Mansion by Kasumigaseki Properties Development: mansion-scale living, garden arrival, wellness amenities, location, and project enquiry. | G5: Dubai Hills Mansion | H5: Dubai Hills Mansion | Residences in Dubai Hills | I5: A mansion-scale residence in Dubai Hills Estate by KPD: garden arrival, private wellness and long-horizon family living, 20 minutes from Downtown. | J5: Dubai Hills Mansion | K5: RealEstateListing, VideoObject, BreadcrumbList | L5: Scale softened by landscape; 'composed rather than oversized'. Estate context (golf, schools) framed as convenience without compromise. | M5: Drafted | N5: 04-dubai-hills-mansion.docx
A6: About Us | B6: ABO | C6: /legacy/about-us.html | D6: /about | E6: About Us | Kasumigaseki Properties Development | F6: About Kasumigaseki Properties Development, its mission, vision, chairman message, and executive management. | G6: Soulful Places Enriched Lives | H6: About KPD | Soulful Places, Enriched Lives | I6: KPD extends Kasumigaseki Capital's Tokyo-listed discipline into Dubai: institutional governance, Japanese craft and one standard at every price point. | J6: Japanese property developer Dubai | K6: AboutPage, Organization | L6: Philosophy forward: Hinshitsu / Anshin / Kakushin; noren principle (handover is the beginning of commitment); 'a better standard is possible for everyone'. | M6: Drafted | N6: 05-about-us.docx
A7: Legacy | B7: LEG | C7: /legacy/legacy.html | D7: /about/legacy | E7: Legacy | Kasumigaseki Properties Development | F7: Explore the legacy of Kasumigaseki Properties Development through a milestone timeline tracing the evolution of the platform, its development discipline, and its current chapter. | G7: A long-horizon platform | H7: Our Legacy | From Tokyo to Dubai | KPD | I7: A long-horizon platform: disciplined capital, measured execution and development value built to hold - from Kasumigaseki Capital to KPD. | J7: Kasumigaseki Capital track record | K7: WebPage | L7: Long-horizon narrative; each timeline beat = capability earned, not scale gained. Direction, not nostalgia. | M7: Drafted | N7: 06-legacy.docx
A8: News & Updates | B8: MED | C8: /legacy/news.html | D8: /news | E8: News | Kasumigaseki Properties Development | F8: KPD news, market notes, development commentary, and project updates. | G8: News and updates | H8: News & Updates | KPD Dubai Real Estate | I8: Announcements, market observations and development commentary from Kasumigaseki Properties Development - a quiet editorial layer on Dubai real estate. | J8: Dubai real estate news | K8: CollectionPage, ItemList | L8: Quiet editorial layer; market observations over press-release tone. External coverage attributed clearly. | M8: Drafted | N8: 07-news-updates.docx
A9: Article pages (blog + news) | B9: BLG/NAR | C9: /legacy/blog-article.html, /legacy/news-article.html | D9: /news/[slug] | E9: Blog Article | Kasumigaseki Properties Development | F9: KPD blog article. | G9: Blog Article | H9: {Article title} | KPD | I9: Per-article: first 150 chars of the article summary, ending on a natural break. | J9: Per-article (set at publish time) | K9: Article (NewsArticle / BlogPosting) | L9: Essayistic but evidentiary; one idea per article; question-shaped openings where natural for AEO. | M9: Drafted | N9: 08-articles.docx
A10: Invest in Dubai | B10: INV | C10: /legacy/invest-in-dubai.html | D10: /invest-in-dubai | E10: Invest in Dubai | Kasumigaseki Properties Development | F10: Invest in Dubai with Kasumigaseki Properties Development through a disciplined residential platform shaped by long-horizon value, location logic, and clear advisory pathways. | G10: Long-horizon value in Dubai | H10: Invest in Dubai Real Estate | KPD Investor Guide | I10: Why Dubai remains investable: regulated freehold ownership, rental yields, Golden Visa routes and KPD's disciplined delivery. Begin a private review. | J10: invest in Dubai real estate | K10: FAQPage, BreadcrumbList | L10: Compliance-safe confidence: 'may be reviewed', 'verify before decisions'. Numbers carry the argument (yields, milestones); KPD credibility = TSE Prime parent. | M10: Drafted | N10: 09-invest-in-dubai.docx
A11: Contact | B11: CON | C11: /legacy/contact.html | D11: /contact | E11: Contact | Kasumigaseki Properties Development | F11: Contact KPD and plan a visit to the KPD Experience Center. | G11: Plan a visit, or start a conversation. | H11: Contact KPD | Experience Center, Business Bay | I11: Plan a visit or start a conversation with KPD. Sales, customer, partner, press and career inquiries - Bay Gate Tower, Floor 36, Business Bay, Dubai. | J11: contact KPD Dubai | K11: ContactPage, Organization (contactPoint) | L11: Anshin in microcopy: unhurried, personal, no obligation. NAP consistency critical for local SEO. | M11: Drafted | N11: 10-contact.docx
A12: Terms of Use | B12: LGL | C12: /legacy/terms.html | D12: /legal/terms | E12: Terms of Use | Kasumigaseki Properties Development | F12: KPD website terms of use. | G12: Terms of Use | H12: Terms of Use | Kasumigaseki Properties Development | I12: The terms governing use of the KPD website and the information presented across project, company, news and contact pages. | J12: KPD terms of use | K12: WebPage | L12: Plain, precise legal register consistent with 'nothing wasted' tone. | M12: Drafted | N12: 11-legal.docx
... A14: Cookie Policy | B14: LGL | C14: /legacy/cookie-policy.html | D14: /legal/cookies | E14: Cookie Policy | Kasumigaseki Properties Development | F14: KPD cookie policy. | G14: Cookie Policy | H14: Cookie Policy | Kasumigaseki Properties Development | I14: How this website uses essential, analytics and preference cookies, and how to manage them through your browser settings. | J14: KPD cookie policy | K14: WebPage | L14: Plain, precise; matches tone of voice without softening substance. | M14: Drafted | N14: 11-legal.docx

Sheet Dashboard
A1: Page | B1: ID | C1: Sections | D1: Drafted | E1: In review | F1: Client edits | G1: Approved | H1: In CMS | I1: % done | J1: Reviewer | K1: Blockers / notes
A2: Header & Navigation | B2: GLB | C2: =COUNTIF('Section Audit'!$C$2:$C$500,$A2) | D2: =COUNTIFS('Section Audit'!$C$2:$C$500,$A2,'Section Audit'!$M$2:$M$500,"Drafted") | E2: =COUNTIFS('Section Audit'!$C$2:$C$500,$A2,'Section Audit'!$M$2:$M$500,"In review") | F2: =COUNTIFS('Section Audit'!$C$2:$C$500,$A2,'Section Audit'!$M$2:$M$500,"Client edits") | G2: =COUNTIFS('Section Audit'!$C$2:$C$500,$A2,'Section Audit'!$M$2:$M$500,"Approved") | H2: =COUNTIFS('Section Audit'!$C$2:$C$500,$A2,'Section Audit'!$M$2:$M$500,"In CMS") | I2: =IF(C2=0,0,(G2+H2)/C2)
A3: Footer | B3: GLB | C3: =COUNTIF('Section Audit'!$C$2:$C$500,$A3) | D3: =COUNTIFS('Section Audit'!$C$2:$C$500,$A3,'Section Audit'!$M$2:$M$500,"Drafted") | E3: =COUNTIFS('Section Audit'!$C$2:$C$500,$A3,'Section Audit'!$M$2:$M$500,"In review") | F3: =COUNTIFS('Section Audit'!$C$2:$C$500,$A3,'Section Audit'!$M$2:$M$500,"Client edits") | G3: =COUNTIFS('Section Audit'!$C$2:$C$500,$A3,'Section Audit'!$M$2:$M$500,"Approved") | H3: =COUNTIFS('Section Audit'!$C$2:$C$500,$A3,'Section Audit'!$M$2:$M$500,"In CMS") | I3: =IF(C3=0,0,(G3+H3)/C3)
A4: Inquiry Form modal (Book online call) | B4: GLB | C4: =COUNTIF('Section Audit'!$C$2:$C$500,$A4) | D4: =COUNTIFS('Section Audit'!$C$2:$C$500,$A4,'Section Audit'!$M$2:$M$500,"Drafted") | E4: =COUNTIFS('Section Audit'!$C$2:$C$500,$A4,'Section Audit'!$M$2:$M$500,"In review") | F4: =COUNTIFS('Section Audit'!$C$2:$C$500,$A4,'Section Audit'!$M$2:$M$500,"Client edits") | G4: =COUNTIFS('Section Audit'!$C$2:$C$500,$A4,'Section Audit'!$M$2:$M$500,"Approved") | H4: =COUNTIFS('Section Audit'!$C$2:$C$500,$A4,'Section Audit'!$M$2:$M$500,"In CMS") | I4: =IF(C4=0,0,(G4+H4)/C4)
A5: Home | B5: HOM | C5: =COUNTIF('Section Audit'!$C$2:$C$500,$A5) | D5: =COUNTIFS('Section Audit'!$C$2:$C$500,$A5,'Section Audit'!$M$2:$M$500,"Drafted") | E5: =COUNTIFS('Section Audit'!$C$2:$C$500,$A5,'Section Audit'!$M$2:$M$500,"In review") | F5: =COUNTIFS('Section Audit'!$C$2:$C$500,$A5,'Section Audit'!$M$2:$M$500,"Client edits") | G5: =COUNTIFS('Section Audit'!$C$2:$C$500,$A5,'Section Audit'!$M$2:$M$500,"Approved") | H5: =COUNTIFS('Section Audit'!$C$2:$C$500,$A5,'Section Audit'!$M$2:$M$500,"In CMS") | I5: =IF(C5=0,0,(G5+H5)/C5)
A6: Seven X Seven | B6: SXS | C6: =COUNTIF('Section Audit'!$C$2:$C$500,$A6) | D6: =COUNTIFS('Section Audit'!$C$2:$C$500,$A6,'Section Audit'!$M$2:$M$500,"Drafted") | E6: =COUNTIFS('Section Audit'!$C$2:$C$500,$A6,'Section Audit'!$M$2:$M$500,"In review") | F6: =COUNTIFS('Section Audit'!$C$2:$C$500,$A6,'Section Audit'!$M$2:$M$500,"Client edits") | G6: =COUNTIFS('Section Audit'!$C$2:$C$500,$A6,'Section Audit'!$M$2:$M$500,"Approved") | H6: =COUNTIFS('Section Audit'!$C$2:$C$500,$A6,'Section Audit'!$M$2:$M$500,"In CMS") | I6: =IF(C6=0,0,(G6+H6)/C6)
A7: Emerald Villa | B7: EVL | C7: =COUNTIF('Section Audit'!$C$2:$C$500,$A7) | D7: =COUNTIFS('Section Audit'!$C$2:$C$500,$A7,'Section Audit'!$M$2:$M$500,"Drafted") | E7: =COUNTIFS('Section Audit'!$C$2:$C$500,$A7,'Section Audit'!$M$2:$M$500,"In review") | F7: =COUNTIFS('Section Audit'!$C$2:$C$500,$A7,'Section Audit'!$M$2:$M$500,"Client edits") | G7: =COUNTIFS('Section Audit'!$C$2:$C$500,$A7,'Section Audit'!$M$2:$M$500,"Approved") | H7: =COUNTIFS('Section Audit'!$C$2:$C$500,$A7,'Section Audit'!$M$2:$M$500,"In CMS") | I7: =IF(C7=0,0,(G7+H7)/C7)
A8: Dubai Hills Mansion | B8: DHM | C8: =COUNTIF('Section Audit'!$C$2:$C$500,$A8) | D8: =COUNTIFS('Section Audit'!$C$2:$C$500,$A8,'Section Audit'!$M$2:$M$500,"Drafted") | E8: =COUNTIFS('Section Audit'!$C$2:$C$500,$A8,'Section Audit'!$M$2:$M$500,"In review") | F8: =COUNTIFS('Section Audit'!$C$2:$C$500,$A8,'Section Audit'!$M$2:$M$500,"Client edits") | G8: =COUNTIFS('Section Audit'!$C$2:$C$500,$A8,'Section Audit'!$M$2:$M$500,"Approved") | H8: =COUNTIFS('Section Audit'!$C$2:$C$500,$A8,'Section Audit'!$M$2:$M$500,"In CMS") | I8: =IF(C8=0,0,(G8+H8)/C8)
A9: About Us | B9: ABO | C9: =COUNTIF('Section Audit'!$C$2:$C$500,$A9) | D9: =COUNTIFS('Section Audit'!$C$2:$C$500,$A9,'Section Audit'!$M$2:$M$500,"Drafted") | E9: =COUNTIFS('Section Audit'!$C$2:$C$500,$A9,'Section Audit'!$M$2:$M$500,"In review") | F9: =COUNTIFS('Section Audit'!$C$2:$C$500,$A9,'Section Audit'!$M$2:$M$500,"Client edits") | G9: =COUNTIFS('Section Audit'!$C$2:$C$500,$A9,'Section Audit'!$M$2:$M$500,"Approved") | H9: =COUNTIFS('Section Audit'!$C$2:$C$500,$A9,'Section Audit'!$M$2:$M$500,"In CMS") | I9: =IF(C9=0,0,(G9+H9)/C9)
A10: Legacy (Our Legacy) | B10: LEG | C10: =COUNTIF('Section Audit'!$C$2:$C$500,$A10) | D10: =COUNTIFS('Section Audit'!$C$2:$C$500,$A10,'Section Audit'!$M$2:$M$500,"Drafted") | E10: =COUNTIFS('Section Audit'!$C$2:$C$500,$A10,'Section Audit'!$M$2:$M$500,"In review") | F10: =COUNTIFS('Section Audit'!$C$2:$C$500,$A10,'Section Audit'!$M$2:$M$500,"Client edits") | G10: =COUNTIFS('Section Audit'!$C$2:$C$500,$A10,'Section Audit'!$M$2:$M$500,"Approved") | H10: =COUNTIFS('Section Audit'!$C$2:$C$500,$A10,'Section Audit'!$M$2:$M$500,"In CMS") | I10: =IF(C10=0,0,(G10+H10)/C10)
A11: News & Updates | B11: MED | C11: =COUNTIF('Section Audit'!$C$2:$C$500,$A11) | D11: =COUNTIFS('Section Audit'!$C$2:$C$500,$A11,'Section Audit'!$M$2:$M$500,"Drafted") | E11: =COUNTIFS('Section Audit'!$C$2:$C$500,$A11,'Section Audit'!$M$2:$M$500,"In review") | F11: =COUNTIFS('Section Audit'!$C$2:$C$500,$A11,'Section Audit'!$M$2:$M$500,"Client edits") | G11: =COUNTIFS('Section Audit'!$C$2:$C$500,$A11,'Section Audit'!$M$2:$M$500,"Approved") | H11: =COUNTIFS('Section Audit'!$C$2:$C$500,$A11,'Section Audit'!$M$2:$M$500,"In CMS") | I11: =IF(C11=0,0,(G11+H11)/C11)
A12: Blog Article (template) | B12: BLG | C12: =COUNTIF('Section Audit'!$C$2:$C$500,$A12) | D12: =COUNTIFS('Section Audit'!$C$2:$C$500,$A12,'Section Audit'!$M$2:$M$500,"Drafted") | E12: =COUNTIFS('Section Audit'!$C$2:$C$500,$A12,'Section Audit'!$M$2:$M$500,"In review") | F12: =COUNTIFS('Section Audit'!$C$2:$C$500,$A12,'Section Audit'!$M$2:$M$500,"Client edits") | G12: =COUNTIFS('Section Audit'!$C$2:$C$500,$A12,'Section Audit'!$M$2:$M$500,"Approved") | H12: =COUNTIFS('Section Audit'!$C$2:$C$500,$A12,'Section Audit'!$M$2:$M$500,"In CMS") | I12: =IF(C12=0,0,(G12+H12)/C12)
A13: News Article (template) | B13: NAR | C13: =COUNTIF('Section Audit'!$C$2:$C$500,$A13) | D13: =COUNTIFS('Section Audit'!$C$2:$C$500,$A13,'Section Audit'!$M$2:$M$500,"Drafted") | E13: =COUNTIFS('Section Audit'!$C$2:$C$500,$A13,'Section Audit'!$M$2:$M$500,"In review") | F13: =COUNTIFS('Section Audit'!$C$2:$C$500,$A13,'Section Audit'!$M$2:$M$500,"Client edits") | G13: =COUNTIFS('Section Audit'!$C$2:$C$500,$A13,'Section Audit'!$M$2:$M$500,"Approved") | H13: =COUNTIFS('Section Audit'!$C$2:$C$500,$A13,'Section Audit'!$M$2:$M$500,"In CMS") | I13: =IF(C13=0,0,(G13+H13)/C13)
... A18: Cookie Policy | B18: LGL | C18: =COUNTIF('Section Audit'!$C$2:$C$500,$A18) | D18: =COUNTIFS('Section Audit'!$C$2:$C$500,$A18,'Section Audit'!$M$2:$M$500,"Drafted") | E18: =COUNTIFS('Section Audit'!$C$2:$C$500,$A18,'Section Audit'!$M$2:$M$500,"In review") | F18: =COUNTIFS('Section Audit'!$C$2:$C$500,$A18,'Section Audit'!$M$2:$M$500,"Client edits") | G18: =COUNTIFS('Section Audit'!$C$2:$C$500,$A18,'Section Audit'!$M$2:$M$500,"Approved") | H18: =COUNTIFS('Section Audit'!$C$2:$C$500,$A18,'Section Audit'!$M$2:$M$500,"In CMS") | I18: =IF(C18=0,0,(G18+H18)/C18)

Sheet Reference
A1: KPD Content Audit — Reference
A3: STATUS LIFECYCLE (dropdown in 'Status' columns)
A4: Not started | B4: Row identified; no rewrite work begun.
A5: Drafted | B5: SEO/AEO rewrite written (in sheet for short copy, in page Doc for long copy).
A6: In review | B6: Sent to client; awaiting feedback.
A7: Client edits | B7: Client left feedback in 'Client feedback' column; revision needed.
A8: Approved | B8: Client approved; ready to enter CMS.
A9: In CMS | B9: Copy entered and saved in the CMS (verify /admin).
A11: WORKING RULES
A12: 1 | B12: Long copy is written ONLY in the page's Google Doc (docs//*.docx are the working Word files). The sheet holds short/medium copy, keywords, metadata, status.
A13: 2 | B13: Meta titles/descriptions live in the 'Page SEO' tab (short, cross-page comparable).
A14: 3 | B14: Client feedback goes ONLY in the 'Client feedback' column (short notes), citing the row ID.
A15: 4 | B15: Do not edit copy in two places. Docs freeze at 'Approved'; the CMS becomes the single source of truth at 'In CMS'.
A16: 5 | B16: Current copy in the tracker is the audit snapshot; legacy xlsx (KPD-Content-Tracker.xlsx) stays untouched.
A18: ID SCHEME
A19: GLB | B19: Header & Navigation, Footer, Inquiry Form modal (Book online call) — 00-globals.md
A20: HOM | B20: Home — 01-home.md
A21: SXS | B21: Seven X Seven — 02-seven-x-seven.md
A22: EVL | B22: Emerald Villa — 03-emerald-villa.md
A23: DHM | B23: Dubai Hills Mansion — 04-dubai-hills-mansion.md
A24: ABO | B24: About Us — 05-about-us.md
A25: LEG | B25: Legacy (Our Legacy) — 06-legacy.md
A26: MED | B26: News & Updates — 07-news-updates.md
A27: BLG | B27: Blog Article (template) — 08-articles.md
A28: NAR | B28: News Article (template) — 08-articles.md
A29: INV | B29: Invest in Dubai — 09-invest-in-dubai.md
A30: CON | B30: Contact — 10-contact.md
A31: LGL | B31: Terms of Use, Privacy Policy, Cookie Policy — 11-legal.md
A33: GOOGLE-DOC TEMPLATES
A34: content/google-doc-templates/ | B34: 12 markdown files (one per page + globals + articles + legal). Paste one per Google Doc; keep the [ID] headings so feedback maps 1:1 to tracker rows.
A36: SEO/AEO AUDIT
A37: Intent values | B37: Informational / Commercial / Transactional / Navigational (dropdown).
A38: AEO question(s) | B38: The People-Also-Ask / AI-Overview style question this section should answer directly. One per row where relevant.
A39: Marketing deck | B39: Distilled into 'Voice/positioning note' on the Page SEO tab once shared.
A40: AEO WITHOUT NEW MODULES
A41: Rule | B41: Front-end stays as-is; no FAQ modules or new sections anywhere.
A42: Investor page FAQ | B42: The existing accordion on Invest in Dubai is the only FAQ UI; stored as a StaticPage content block + FAQPage JSON-LD in the page head.
A43: All other pages | B43: Question-shaped H2/H3s + 40-60 word answer-first paragraphs within existing sections (driven by the AEO question(s) column).
A44: Long-tail Q&A | B44: Published as Articles (BLOG kind) in the CMS, internally linked to development pages.
